LICENSE
MANIFEST.in
README.rst
requirements.txt
requirements_dev.txt
setup.cfg
setup.py
docs/Makefile
docs/conf.py
docs/getting-started.rst
docs/index.rst
docs/make.bat
docs/source/example.rst
docs/source/iter_karld_tools.rst
docs/source/iter_karld_tools.tests.rst
iter_karld_tools/__init__.py
iter_karld_tools/_meta.py
iter_karld_tools.egg-info/PKG-INFO
iter_karld_tools.egg-info/SOURCES.txt
iter_karld_tools.egg-info/dependency_links.txt
iter_karld_tools.egg-info/top_level.txt
iter_karld_tools/tests/__init__.py
iter_karld_tools/tests/test_iter_tools.py