Metadata-Version: 1.1
Name: iter_karld_tools
Version: 0.9.2
Summary: More tools for iterators
Home-page: https://github.com/johnwlockwood/iter_karld_tools
Author: John W Lockwood IV
Author-email: john@tackletronics.com
License:                                  Apache License
